{
  "lake_polygon": [
    [
      46.651179,
      -73.519533
    ],
    [
      46.651139,
      -73.519483
    ],
    [
      46.651139,
      -73.519373
    ],
    [
      46.651058,
      -73.519253
    ],
    [
      46.650979,
      -73.519023
    ],
    [
      46.650918,
      -73.518902
    ],
    [
      46.650659,
      -73.518672
    ],
    [
      46.650559,
      -73.518602
    ],
    [
      46.650239,
      -73.518562
    ],
    [
      46.65013,
      -73.518592
    ],
    [
      46.650009,
      -73.518641
    ],
    [
      46.649829,
      -73.518781
    ],
    [
      46.649759,
      -73.518992
    ],
    [
      46.64975,
      -73.519142
    ],
    [
      46.64977,
      -73.519273
    ],
    [
      46.64984,
      -73.519452
    ],
    [
      46.64998,
      -73.519573
    ],
    [
      46.65004,
      -73.519653
    ],
    [
      46.650059,
      -73.519723
    ],
    [
      46.650039,
      -73.519823
    ],
    [
      46.64992,
      -73.520004
    ],
    [
      46.64995,
      -73.520183
    ],
    [
      46.64992,
      -73.520334
    ],
    [
      46.649879,
      -73.520523
    ],
    [
      46.64989,
      -73.520614
    ],
    [
      46.649869,
      -73.520683
    ],
    [
      46.64965,
      -73.520895
    ],
    [
      46.64957,
      -73.520995
    ],
    [
      46.64946,
      -73.521283
    ],
    [
      46.64942,
      -73.521595
    ],
    [
      46.64942,
      -73.521754
    ],
    [
      46.64961,
      -73.522427
    ],
    [
      46.64968,
      -73.522516
    ],
    [
      46.649829,
      -73.522877
    ],
    [
      46.649899,
      -73.523117
    ],
    [
      46.64993,
      -73.523258
    ],
    [
      46.64995,
      -73.523297
    ],
    [
      46.649979,
      -73.523296
    ],
    [
      46.65009,
      -73.523136
    ],
    [
      46.650159,
      -73.522997
    ],
    [
      46.65057,
      -73.522576
    ],
    [
      46.650839,
      -73.522325
    ],
    [
      46.650999,
      -73.522216
    ],
    [
      46.65107,
      -73.522126
    ],
    [
      46.651138,
      -73.522026
    ],
    [
      46.651199,
      -73.521916
    ],
    [
      46.651219,
      -73.521665
    ],
    [
      46.651289,
      -73.521444
    ],
    [
      46.651259,
      -73.521314
    ],
    [
      46.651219,
      -73.521235
    ],
    [
      46.651039,
      -73.521043
    ],
    [
      46.651,
      -73.520954
    ],
    [
      46.651018,
      -73.520864
    ],
    [
      46.651098,
      -73.520825
    ],
    [
      46.651309,
      -73.520843
    ],
    [
      46.651409,
      -73.520845
    ],
    [
      46.651499,
      -73.520805
    ],
    [
      46.651578,
      -73.520723
    ],
    [
      46.651808,
      -73.520393
    ],
    [
      46.651888,
      -73.520103
    ],
    [
      46.651888,
      -73.519952
    ],
    [
      46.651859,
      -73.519803
    ],
    [
      46.651718,
      -73.519523
    ],
    [
      46.651628,
      -73.519423
    ],
    [
      46.651419,
      -73.519363
    ],
    [
      46.651338,
      -73.519372
    ],
    [
      46.651269,
      -73.519413
    ]
  ],
  "waterways": [
    {
      "coords": [
        [
          46.651718,
          -73.517873
        ],
        [
          46.651728,
          -73.517841
        ],
        [
          46.651728,
          -73.517839
        ]
      ],
      "center_lat": 46.65172466666667,
      "center_lon": -73.517851,
      "type": "inlet"
    },
    {
      "coords": [
        [
          46.648898,
          -73.521888
        ],
        [
          46.648921,
          -73.521885
        ],
        [
          46.648922,
          -73.521885
        ]
      ],
      "center_lat": 46.648913666666665,
      "center_lon": -73.521886,
      "type": "outlet"
    },
    {
      "coords": [
        [
          46.648922,
          -73.520315
        ],
        [
          46.64892,
          -73.520313
        ],
        [
          46.648899,
          -73.520298
        ]
      ],
      "center_lat": 46.648913666666665,
      "center_lon": -73.52030866666666,
      "type": "outlet"
    },
    {
      "coords": [
        [
          46.64972,
          -73.524309
        ],
        [
          46.64978,
          -73.524137
        ],
        [
          46.649869,
          -73.523638
        ],
        [
          46.64995,
          -73.523297
        ]
      ],
      "center_lat": 46.649829749999995,
      "center_lon": -73.52384525000001,
      "type": "tributary"
    }
  ],
  "fishing_spots": [],
  "boat_access": [
    {
      "lat": 46.650025,
      "lon": -73.523228
    }
  ],
  "portage": [],
  "trout_line": [
    [
      46.650953,
      -73.521382
    ],
    [
      46.650918,
      -73.521374
    ],
    [
      46.650887,
      -73.521355
    ],
    [
      46.650861,
      -73.521327
    ],
    [
      46.650838,
      -73.521303
    ],
    [
      46.650818,
      -73.521269
    ],
    [
      46.650801,
      -73.521234
    ],
    [
      46.650776,
      -73.521177
    ],
    [
      46.650761,
      -73.521106
    ],
    [
      46.650754,
      -73.521042
    ],
    [
      46.650749,
      -73.520985
    ],
    [
      46.650743,
      -73.520916
    ],
    [
      46.650756,
      -73.520865
    ],
    [
      46.650768,
      -73.520816
    ],
    [
      46.650798,
      -73.520771
    ],
    [
      46.650823,
      -73.520732
    ],
    [
      46.650859,
      -73.52068
    ],
    [
      46.650904,
      -73.520637
    ],
    [
      46.650949,
      -73.520603
    ],
    [
      46.650989,
      -73.520575
    ],
    [
      46.651031,
      -73.520552
    ],
    [
      46.651072,
      -73.520537
    ],
    [
      46.651116,
      -73.520521
    ],
    [
      46.65116,
      -73.520515
    ],
    [
      46.651206,
      -73.520518
    ],
    [
      46.650394,
      -73.522179
    ],
    [
      46.650354,
      -73.522234
    ],
    [
      46.650312,
      -73.522277
    ],
    [
      46.650265,
      -73.522309
    ],
    [
      46.650223,
      -73.522341
    ],
    [
      46.650174,
      -73.522365
    ],
    [
      46.650126,
      -73.522375
    ],
    [
      46.650078,
      -73.522383
    ],
    [
      46.650027,
      -73.522382
    ],
    [
      46.649981,
      -73.522366
    ],
    [
      46.649935,
      -73.522351
    ],
    [
      46.649886,
      -73.522326
    ],
    [
      46.64985,
      -73.522285
    ],
    [
      46.649815,
      -73.522242
    ],
    [
      46.64979,
      -73.522174
    ],
    [
      46.649769,
      -73.52211
    ],
    [
      46.649748,
      -73.522046
    ],
    [
      46.649734,
      -73.521974
    ],
    [
      46.64973,
      -73.521903
    ],
    [
      46.649724,
      -73.521828
    ],
    [
      46.649731,
      -73.521748
    ],
    [
      46.649743,
      -73.521674
    ],
    [
      46.649756,
      -73.521601
    ],
    [
      46.649775,
      -73.52153
    ],
    [
      46.649803,
      -73.521462
    ],
    [
      46.650154,
      -73.519723
    ],
    [
      46.650139,
      -73.519675
    ],
    [
      46.650128,
      -73.519624
    ],
    [
      46.65012,
      -73.519573
    ],
    [
      46.650112,
      -73.519522
    ],
    [
      46.650108,
      -73.519472
    ],
    [
      46.650106,
      -73.519421
    ],
    [
      46.650103,
      -73.519345
    ],
    [
      46.650105,
      -73.519268
    ],
    [
      46.650115,
      -73.519195
    ],
    [
      46.650119,
      -73.519159
    ],
    [
      46.650122,
      -73.519119
    ],
    [
      46.650133,
      -73.519088
    ],
    [
      46.650144,
      -73.519063
    ],
    [
      46.65016,
      -73.519043
    ],
    [
      46.650175,
      -73.519025
    ],
    [
      46.650198,
      -73.519
    ],
    [
      46.650229,
      -73.518985
    ],
    [
      46.650257,
      -73.518976
    ],
    [
      46.650281,
      -73.518969
    ],
    [
      46.650307,
      -73.518966
    ],
    [
      46.650331,
      -73.518969
    ],
    [
      46.650356,
      -73.518973
    ],
    [
      46.650382,
      -73.518983
    ],
    [
      46.650405,
      -73.519001
    ]
  ],
  "access_path": [],
  "lake_center": {
    "lat": 46.65057782089551,
    "lon": -73.52062570149253
  },
  "lake_bbox": {
    "S": 46.64942,
    "N": 46.651888,
    "W": -73.523297,
    "E": -73.518562
  },
  "mffp_isobaths": [
    {
      "depth_m": 1.5,
      "depth_ft": 5.0,
      "coords": [
        [
          46.650091,
          -73.522768
        ],
        [
          46.65007,
          -73.522795
        ],
        [
          46.650048,
          -73.52284
        ],
        [
          46.650025,
          -73.522865
        ],
        [
          46.650004,
          -73.522863
        ],
        [
          46.649982,
          -73.52284
        ],
        [
          46.649969,
          -73.522785
        ],
        [
          46.649958,
          -73.522723
        ],
        [
          46.64995,
          -73.522677
        ],
        [
          46.649926,
          -73.522624
        ],
        [
          46.649894,
          -73.522578
        ],
        [
          46.64985,
          -73.522502
        ],
        [
          46.649822,
          -73.522441
        ],
        [
          46.649801,
          -73.522362
        ],
        [
          46.649782,
          -73.522263
        ],
        [
          46.649762,
          -73.522175
        ],
        [
          46.64974,
          -73.522122
        ],
        [
          46.6497,
          -73.52205
        ],
        [
          46.649666,
          -73.521953
        ],
        [
          46.649641,
          -73.521854
        ],
        [
          46.649629,
          -73.521684
        ],
        [
          46.649626,
          -73.521578
        ],
        [
          46.649631,
          -73.521485
        ],
        [
          46.649646,
          -73.521332
        ],
        [
          46.649665,
          -73.521229
        ],
        [
          46.649676,
          -73.521169
        ],
        [
          46.649716,
          -73.521095
        ],
        [
          46.649787,
          -73.521011
        ],
        [
          46.649868,
          -73.52094
        ],
        [
          46.649984,
          -73.520873
        ],
        [
          46.650117,
          -73.5208
        ],
        [
          46.650185,
          -73.520745
        ],
        [
          46.650245,
          -73.520679
        ],
        [
          46.650299,
          -73.520612
        ],
        [
          46.650344,
          -73.520526
        ],
        [
          46.650363,
          -73.520464
        ],
        [
          46.650362,
          -73.520406
        ],
        [
          46.650351,
          -73.520338
        ],
        [
          46.650321,
          -73.520259
        ],
        [
          46.650294,
          -73.520211
        ],
        [
          46.650257,
          -73.520145
        ],
        [
          46.650227,
          -73.520093
        ],
        [
          46.650205,
          -73.520001
        ],
        [
          46.650194,
          -73.51991
        ],
        [
          46.650195,
          -73.51983
        ],
        [
          46.650207,
          -73.519724
        ],
        [
          46.650243,
          -73.519543
        ],
        [
          46.650278,
          -73.519423
        ],
        [
          46.650318,
          -73.519329
        ],
        [
          46.650368,
          -73.519252
        ],
        [
          46.650411,
          -73.519211
        ],
        [
          46.650459,
          -73.519179
        ],
        [
          46.650503,
          -73.519164
        ],
        [
          46.650568,
          -73.519167
        ],
        [
          46.650623,
          -73.51919
        ],
        [
          46.650666,
          -73.519215
        ],
        [
          46.650736,
          -73.519304
        ],
        [
          46.650825,
          -73.519443
        ],
        [
          46.650913,
          -73.519558
        ],
        [
          46.651006,
          -73.519664
        ],
        [
          46.651088,
          -73.519762
        ],
        [
          46.651139,
          -73.519809
        ],
        [
          46.651197,
          -73.519849
        ],
        [
          46.651278,
          -73.519883
        ],
        [
          46.651356,
          -73.519885
        ],
        [
          46.651421,
          -73.519879
        ],
        [
          46.651512,
          -73.519845
        ],
        [
          46.65159,
          -73.519841
        ],
        [
          46.651634,
          -73.51988
        ],
        [
          46.651675,
          -73.519956
        ],
        [
          46.651693,
          -73.520046
        ],
        [
          46.651691,
          -73.520126
        ],
        [
          46.651674,
          -73.520204
        ],
        [
          46.651643,
          -73.52028
        ],
        [
          46.651587,
          -73.520337
        ],
        [
          46.65154,
          -73.520356
        ],
        [
          46.651479,
          -73.520347
        ],
        [
          46.651407,
          -73.520316
        ],
        [
          46.651324,
          -73.520258
        ],
        [
          46.651054,
          -73.520004
        ],
        [
          46.65098,
          -73.519924
        ],
        [
          46.650932,
          -73.519874
        ],
        [
          46.650885,
          -73.519858
        ],
        [
          46.650824,
          -73.519869
        ],
        [
          46.650781,
          -73.519923
        ],
        [
          46.650756,
          -73.519983
        ],
        [
          46.650753,
          -73.520057
        ],
        [
          46.650793,
          -73.520137
        ],
        [
          46.650874,
          -73.520233
        ],
        [
          46.650998,
          -73.520353
        ],
        [
          46.651151,
          -73.520522
        ],
        [
          46.651199,
          -73.520585
        ],
        [
          46.651209,
          -73.520644
        ],
        [
          46.651203,
          -73.520682
        ],
        [
          46.651178,
          -73.520723
        ],
        [
          46.651122,
          -73.520755
        ],
        [
          46.650913,
          -73.520843
        ],
        [
          46.650846,
          -73.520878
        ],
        [
          46.65079,
          -73.520919
        ],
        [
          46.650739,
          -73.52095
        ],
        [
          46.650709,
          -73.521008
        ],
        [
          46.650701,
          -73.521059
        ],
        [
          46.65072,
          -73.521114
        ],
        [
          46.650783,
          -73.521199
        ],
        [
          46.650837,
          -73.521257
        ],
        [
          46.650891,
          -73.521282
        ],
        [
          46.650947,
          -73.52134
        ],
        [
          46.650992,
          -73.521406
        ],
        [
          46.651008,
          -73.521492
        ],
        [
          46.651,
          -73.521611
        ],
        [
          46.650952,
          -73.52175
        ],
        [
          46.650887,
          -73.521894
        ],
        [
          46.650822,
          -73.521982
        ],
        [
          46.650734,
          -73.522071
        ],
        [
          46.650674,
          -73.522145
        ],
        [
          46.650635,
          -73.522222
        ],
        [
          46.65059,
          -73.52234
        ],
        [
          46.650566,
          -73.522387
        ],
        [
          46.650536,
          -73.522419
        ],
        [
          46.650462,
          -73.52245
        ],
        [
          46.650405,
          -73.522467
        ],
        [
          46.65034,
          -73.522504
        ],
        [
          46.650291,
          -73.522543
        ],
        [
          46.650209,
          -73.522619
        ],
        [
          46.650152,
          -73.52268
        ],
        [
          46.65011,
          -73.522739
        ]
      ]
    },
    {
      "depth_m": 3.0,
      "depth_ft": 10.0,
      "coords": [
        [
          46.649931,
          -73.522524
        ],
        [
          46.649929,
          -73.522502
        ],
        [
          46.649934,
          -73.522429
        ],
        [
          46.649937,
          -73.522393
        ],
        [
          46.649934,
          -73.52236
        ],
        [
          46.649905,
          -73.522304
        ],
        [
          46.649863,
          -73.52224
        ],
        [
          46.649831,
          -73.522166
        ],
        [
          46.649739,
          -73.521954
        ],
        [
          46.649706,
          -73.521859
        ],
        [
          46.649691,
          -73.521776
        ],
        [
          46.649692,
          -73.521678
        ],
        [
          46.649702,
          -73.52162
        ],
        [
          46.649743,
          -73.521497
        ],
        [
          46.649781,
          -73.52141
        ],
        [
          46.649824,
          -73.521324
        ],
        [
          46.649869,
          -73.521257
        ],
        [
          46.64992,
          -73.521196
        ],
        [
          46.649985,
          -73.521123
        ],
        [
          46.650057,
          -73.521052
        ],
        [
          46.650123,
          -73.521004
        ],
        [
          46.650201,
          -73.52094
        ],
        [
          46.650275,
          -73.520865
        ],
        [
          46.650322,
          -73.520817
        ],
        [
          46.650376,
          -73.520747
        ],
        [
          46.650417,
          -73.520681
        ],
        [
          46.650444,
          -73.520623
        ],
        [
          46.650456,
          -73.520579
        ],
        [
          46.650458,
          -73.520536
        ],
        [
          46.650453,
          -73.520503
        ],
        [
          46.650431,
          -73.520468
        ],
        [
          46.650416,
          -73.52044
        ],
        [
          46.650405,
          -73.520409
        ],
        [
          46.650404,
          -73.520363
        ],
        [
          46.650404,
          -73.52033
        ],
        [
          46.650391,
          -73.520283
        ],
        [
          46.650371,
          -73.520244
        ],
        [
          46.650344,
          -73.520203
        ],
        [
          46.650324,
          -73.520135
        ],
        [
          46.650279,
          -73.519992
        ],
        [
          46.650263,
          -73.519928
        ],
        [
          46.650263,
          -73.519837
        ],
        [
          46.650283,
          -73.519728
        ],
        [
          46.650306,
          -73.519628
        ],
        [
          46.650325,
          -73.519581
        ],
        [
          46.650382,
          -73.519511
        ],
        [
          46.65044,
          -73.519471
        ],
        [
          46.650476,
          -73.519464
        ],
        [
          46.650536,
          -73.519487
        ],
        [
          46.650625,
          -73.519573
        ],
        [
          46.650701,
          -73.519655
        ],
        [
          46.65072,
          -73.519696
        ],
        [
          46.650727,
          -73.519749
        ],
        [
          46.650721,
          -73.519814
        ],
        [
          46.650706,
          -73.519903
        ],
        [
          46.650683,
          -73.51999
        ],
        [
          46.650664,
          -73.520077
        ],
        [
          46.650671,
          -73.520147
        ],
        [
          46.650694,
          -73.520204
        ],
        [
          46.650739,
          -73.520272
        ],
        [
          46.650832,
          -73.520356
        ],
        [
          46.650903,
          -73.520425
        ],
        [
          46.650971,
          -73.520487
        ],
        [
          46.651008,
          -73.520535
        ],
        [
          46.651016,
          -73.520568
        ],
        [
          46.651017,
          -73.520623
        ],
        [
          46.651005,
          -73.520668
        ],
        [
          46.650979,
          -73.520688
        ],
        [
          46.65093,
          -73.52073
        ],
        [
          46.650852,
          -73.520767
        ],
        [
          46.65079,
          -73.5208
        ],
        [
          46.650742,
          -73.520834
        ],
        [
          46.650676,
          -73.520883
        ],
        [
          46.650629,
          -73.520939
        ],
        [
          46.650604,
          -73.520991
        ],
        [
          46.650591,
          -73.521042
        ],
        [
          46.65059,
          -73.521106
        ],
        [
          46.650616,
          -73.521174
        ],
        [
          46.650656,
          -73.521253
        ],
        [
          46.650711,
          -73.521338
        ],
        [
          46.650757,
          -73.521423
        ],
        [
          46.65078,
          -73.521496
        ],
        [
          46.65079,
          -73.521584
        ],
        [
          46.650776,
          -73.521671
        ],
        [
          46.650735,
          -73.521802
        ],
        [
          46.650674,
          -73.521955
        ],
        [
          46.650608,
          -73.522101
        ],
        [
          46.650547,
          -73.522211
        ],
        [
          46.650506,
          -73.522267
        ],
        [
          46.650455,
          -73.522333
        ],
        [
          46.650409,
          -73.522385
        ],
        [
          46.650367,
          -73.522419
        ],
        [
          46.650305,
          -73.522479
        ],
        [
          46.650257,
          -73.52252
        ],
        [
          46.650195,
          -73.522557
        ],
        [
          46.65013,
          -73.522596
        ],
        [
          46.650078,
          -73.52262
        ],
        [
          46.650036,
          -73.522634
        ],
        [
          46.650007,
          -73.522635
        ],
        [
          46.64998,
          -73.522634
        ],
        [
          46.649955,
          -73.522617
        ],
        [
          46.649939,
          -73.522582
        ],
        [
          46.649931,
          -73.522544
        ]
      ]
    },
    {
      "depth_m": 4.6,
      "depth_ft": 15.0,
      "coords": [
        [
          46.649945,
          -73.522183
        ],
        [
          46.649923,
          -73.522155
        ],
        [
          46.649878,
          -73.522072
        ],
        [
          46.64983,
          -73.521998
        ],
        [
          46.649794,
          -73.521912
        ],
        [
          46.649762,
          -73.521851
        ],
        [
          46.649747,
          -73.521807
        ],
        [
          46.649741,
          -73.521741
        ],
        [
          46.649762,
          -73.52167
        ],
        [
          46.649789,
          -73.521569
        ],
        [
          46.649841,
          -73.521461
        ],
        [
          46.649898,
          -73.521358
        ],
        [
          46.649984,
          -73.521236
        ],
        [
          46.650063,
          -73.521152
        ],
        [
          46.650157,
          -73.521074
        ],
        [
          46.650245,
          -73.521021
        ],
        [
          46.650325,
          -73.520936
        ],
        [
          46.650395,
          -73.520839
        ],
        [
          46.650443,
          -73.52076
        ],
        [
          46.650477,
          -73.520682
        ],
        [
          46.650497,
          -73.520584
        ],
        [
          46.650508,
          -73.520504
        ],
        [
          46.650491,
          -73.520458
        ],
        [
          46.650465,
          -73.52039
        ],
        [
          46.650443,
          -73.520322
        ],
        [
          46.650411,
          -73.520154
        ],
        [
          46.65039,
          -73.520058
        ],
        [
          46.650369,
          -73.519987
        ],
        [
          46.650356,
          -73.519923
        ],
        [
          46.650352,
          -73.519864
        ],
        [
          46.650362,
          -73.519781
        ],
        [
          46.650387,
          -73.519723
        ],
        [
          46.650411,
          -73.519692
        ],
        [
          46.650452,
          -73.519688
        ],
        [
          46.650514,
          -73.5197
        ],
        [
          46.650553,
          -73.519714
        ],
        [
          46.650587,
          -73.519758
        ],
        [
          46.650606,
          -73.519806
        ],
        [
          46.650608,
          -73.51987
        ],
        [
          46.650608,
          -73.519959
        ],
        [
          46.650607,
          -73.520016
        ],
        [
          46.650607,
          -73.520067
        ],
        [
          46.650615,
          -73.520151
        ],
        [
          46.650634,
          -73.52023
        ],
        [
          46.650665,
          -73.520318
        ],
        [
          46.650689,
          -73.520377
        ],
        [
          46.650713,
          -73.52043
        ],
        [
          46.650719,
          -73.520476
        ],
        [
          46.65072,
          -73.520523
        ],
        [
          46.650695,
          -73.520623
        ],
        [
          46.65067,
          -73.520706
        ],
        [
          46.650632,
          -73.520782
        ],
        [
          46.65059,
          -73.520863
        ],
        [
          46.65055,
          -73.520944
        ],
        [
          46.650533,
          -73.521004
        ],
        [
          46.65052,
          -73.521073
        ],
        [
          46.650519,
          -73.521148
        ],
        [
          46.650525,
          -73.521234
        ],
        [
          46.650532,
          -73.521312
        ],
        [
          46.650553,
          -73.521411
        ],
        [
          46.650566,
          -73.521497
        ],
        [
          46.650572,
          -73.521601
        ],
        [
          46.650569,
          -73.521707
        ],
        [
          46.650556,
          -73.521849
        ],
        [
          46.650529,
          -73.522038
        ],
        [
          46.650509,
          -73.52213
        ],
        [
          46.650481,
          -73.52219
        ],
        [
          46.650445,
          -73.522238
        ],
        [
          46.650392,
          -73.522279
        ],
        [
          46.650338,
          -73.522309
        ],
        [
          46.650282,
          -73.522333
        ],
        [
          46.650238,
          -73.522341
        ],
        [
          46.650192,
          -73.522338
        ],
        [
          46.650132,
          -73.522311
        ],
        [
          46.650088,
          -73.522285
        ],
        [
          46.650046,
          -73.522258
        ],
        [
          46.65001,
          -73.522234
        ],
        [
          46.649967,
          -73.522209
        ]
      ]
    },
    {
      "depth_m": 6.1,
      "depth_ft": 20.0,
      "coords": [
        [
          46.649934,
          -73.522068
        ],
        [
          46.649911,
          -73.522046
        ],
        [
          46.649872,
          -73.521994
        ],
        [
          46.649838,
          -73.521922
        ],
        [
          46.649814,
          -73.521856
        ],
        [
          46.649801,
          -73.521788
        ],
        [
          46.649799,
          -73.521744
        ],
        [
          46.649803,
          -73.521686
        ],
        [
          46.649819,
          -73.521613
        ],
        [
          46.64985,
          -73.521525
        ],
        [
          46.649911,
          -73.521424
        ],
        [
          46.649939,
          -73.52139
        ],
        [
          46.649999,
          -73.521309
        ],
        [
          46.650058,
          -73.521238
        ],
        [
          46.650115,
          -73.521184
        ],
        [
          46.650168,
          -73.521151
        ],
        [
          46.650257,
          -73.521129
        ],
        [
          46.650323,
          -73.521118
        ],
        [
          46.650378,
          -73.521139
        ],
        [
          46.650407,
          -73.521169
        ],
        [
          46.650437,
          -73.521266
        ],
        [
          46.650476,
          -73.521429
        ],
        [
          46.650492,
          -73.52153
        ],
        [
          46.650501,
          -73.521605
        ],
        [
          46.650499,
          -73.521687
        ],
        [
          46.65048,
          -73.521783
        ],
        [
          46.650451,
          -73.521863
        ],
        [
          46.650412,
          -73.521949
        ],
        [
          46.650377,
          -73.521998
        ],
        [
          46.650322,
          -73.522053
        ],
        [
          46.650265,
          -73.522092
        ],
        [
          46.650214,
          -73.522113
        ],
        [
          46.650156,
          -73.522137
        ],
        [
          46.650115,
          -73.522136
        ],
        [
          46.650069,
          -73.522135
        ],
        [
          46.650007,
          -73.522117
        ],
        [
          46.649959,
          -73.522092
        ]
      ]
    },
    {
      "depth_m": 7.6,
      "depth_ft": 25.0,
      "coords": [
        [
          46.649925,
          -73.5219
        ],
        [
          46.649904,
          -73.521874
        ],
        [
          46.649878,
          -73.521819
        ],
        [
          46.649856,
          -73.521775
        ],
        [
          46.649846,
          -73.521729
        ],
        [
          46.649841,
          -73.521674
        ],
        [
          46.649852,
          -73.521618
        ],
        [
          46.64988,
          -73.521544
        ],
        [
          46.649927,
          -73.521468
        ],
        [
          46.649974,
          -73.521396
        ],
        [
          46.650043,
          -73.521307
        ],
        [
          46.650113,
          -73.52125
        ],
        [
          46.650146,
          -73.521225
        ],
        [
          46.650185,
          -73.521222
        ],
        [
          46.65024,
          -73.521231
        ],
        [
          46.650302,
          -73.521267
        ],
        [
          46.650334,
          -73.521317
        ],
        [
          46.650357,
          -73.521401
        ],
        [
          46.650373,
          -73.52146
        ],
        [
          46.650389,
          -73.521533
        ],
        [
          46.650408,
          -73.521603
        ],
        [
          46.650415,
          -73.521667
        ],
        [
          46.650414,
          -73.521716
        ],
        [
          46.650396,
          -73.52175
        ],
        [
          46.650367,
          -73.521768
        ],
        [
          46.650337,
          -73.52178
        ],
        [
          46.650307,
          -73.521774
        ],
        [
          46.650288,
          -73.521753
        ],
        [
          46.650265,
          -73.521742
        ],
        [
          46.650239,
          -73.52175
        ],
        [
          46.650208,
          -73.521777
        ],
        [
          46.650175,
          -73.521853
        ],
        [
          46.650152,
          -73.521911
        ],
        [
          46.650128,
          -73.521963
        ],
        [
          46.650102,
          -73.521979
        ],
        [
          46.650064,
          -73.521985
        ],
        [
          46.650029,
          -73.521981
        ],
        [
          46.65,
          -73.521975
        ],
        [
          46.649974,
          -73.521958
        ],
        [
          46.649943,
          -73.521926
        ]
      ]
    },
    {
      "depth_m": 9.1,
      "depth_ft": 30.0,
      "coords": [
        [
          46.649879,
          -73.521704
        ],
        [
          46.649881,
          -73.521693
        ],
        [
          46.649891,
          -73.52165
        ],
        [
          46.649935,
          -73.521565
        ],
        [
          46.65,
          -73.521468
        ],
        [
          46.65005,
          -73.521389
        ],
        [
          46.650082,
          -73.521351
        ],
        [
          46.650106,
          -73.521343
        ],
        [
          46.650134,
          -73.521351
        ],
        [
          46.650158,
          -73.521371
        ],
        [
          46.650198,
          -73.521396
        ],
        [
          46.650233,
          -73.521411
        ],
        [
          46.65026,
          -73.52145
        ],
        [
          46.650288,
          -73.521509
        ],
        [
          46.650318,
          -73.52157
        ],
        [
          46.650329,
          -73.521612
        ],
        [
          46.650329,
          -73.521643
        ],
        [
          46.650313,
          -73.521681
        ],
        [
          46.650292,
          -73.521693
        ],
        [
          46.650261,
          -73.521698
        ],
        [
          46.650224,
          -73.521708
        ],
        [
          46.650196,
          -73.521731
        ],
        [
          46.650175,
          -73.521742
        ],
        [
          46.650146,
          -73.521745
        ],
        [
          46.650117,
          -73.521735
        ],
        [
          46.650089,
          -73.521692
        ],
        [
          46.650069,
          -73.521668
        ],
        [
          46.650052,
          -73.521666
        ],
        [
          46.650033,
          -73.521684
        ],
        [
          46.650014,
          -73.521736
        ],
        [
          46.649998,
          -73.521783
        ],
        [
          46.649974,
          -73.521805
        ],
        [
          46.649942,
          -73.521815
        ],
        [
          46.649913,
          -73.521798
        ],
        [
          46.649894,
          -73.521772
        ],
        [
          46.649885,
          -73.521753
        ],
        [
          46.64988,
          -73.521717
        ]
      ]
    }
  ]
}